pykemon/__init__.py
pykemon/api.py
pykemon/exceptions.py
pykemon/models.py
pykemon/request.py
pykemon/resources.py
pykemon-0.2.0.dist-info/DESCRIPTION.rst
pykemon-0.2.0.dist-info/METADATA
pykemon-0.2.0.dist-info/RECORD
pykemon-0.2.0.dist-info/WHEEL
pykemon-0.2.0.dist-info/metadata.json
pykemon-0.2.0.dist-info/top_level.txt
