Metadata-Version: 2.0
Name: pykemon
Version: 0.2.0
Summary: A Python wrapper for PokeAPI
Home-page: https://github.com/phalt/pykemon
Author: Paul Hallett
Author-email: hello@phalt.co
License: BSD
Keywords: pykemon
Platform: UNKNOWN
Classifier: Development Status :: 4 - Beta
Classifier: Intended Audience :: Developers
Classifier: License :: OSI Approved :: BSD License
Classifier: Natural Language :: English
Classifier: Programming Language :: Python :: 2
Classifier: Programming Language :: Python :: 2.7
Requires-Dist: beckett (==0.4.0)
Requires-Dist: requests (==2.10.0)
Requires-Dist: simplejson (==3.3.1)
